fugle_trade/__init__.py
fugle_trade/constant.py
fugle_trade/init.py
fugle_trade/order.py
fugle_trade/sdk.py
fugle_trade/util.py
fugle_trade/websocket.py
fugle_trade-1.2.0.dist-info/LICENSE
fugle_trade-1.2.0.dist-info/METADATA
fugle_trade-1.2.0.dist-info/WHEEL
fugle_trade-1.2.0.dist-info/RECORD
