Metadata-Version: 2.1
Name: fugle-trade
Version: 1.2.0
Summary: 
Home-page: https://github.com/fugle-dev/fugle-trade-python#readme
License: MIT
Keywords: fugle,trade,stock
Author: Fortuna Intelligence Co., Ltd.
Author-email: development@fugle.tw
Requires-Python: >=3.7,<4.0
Classifier: License :: OSI Approved :: MIT License
Classifier: Programming Language :: Python :: 3
Classifier: Programming Language :: Python :: 3.7
Classifier: Programming Language :: Python :: 3.8
Classifier: Programming Language :: Python :: 3.9
Classifier: Programming Language :: Python :: 3.10
Classifier: Programming Language :: Python :: 3.11
Requires-Dist: fugle-trade-core (==2.1.0)
Requires-Dist: keyring (==23.5.0)
Requires-Dist: keyrings.cryptfile (==1.3.8)
Requires-Dist: websocket-client (>=1.2.1,<2.0.0)
Project-URL: Documentation, https://developer.fugle.tw/docs/trading/intro
Project-URL: Repository, https://github.com/fugle-dev/fugle-trade-python
